unifhycontrib_rfm-0.1.1-py3.8-nspkg.pth
unifhycontrib/rfm/__init__.py
unifhycontrib/rfm/openwater.py
unifhycontrib/rfm/version.py
unifhycontrib_rfm-0.1.1.dist-info/METADATA
unifhycontrib_rfm-0.1.1.dist-info/WHEEL
unifhycontrib_rfm-0.1.1.dist-info/namespace_packages.txt
unifhycontrib_rfm-0.1.1.dist-info/top_level.txt
unifhycontrib_rfm-0.1.1.dist-info/RECORD
