Metadata-Version: 2.1
Name: unifhycontrib-rfm
Version: 0.1.1
Summary: unifhy components for the RFM model
Author: Huw Lewis, Thibault Hallouin
License: UK Open Government
Project-URL: Source Code, https://github.com/unifhy-org/unifhycontrib-rfm
Platform: UNKNOWN
Classifier: Development Status :: 4 - Beta
Classifier: Natural Language :: English
Classifier: Topic :: Scientific/Engineering :: Hydrology
Requires-Dist: unifhy (>=0.1.0)
